anomaly_detection_methods/__init__.py
anomaly_detection_methods/ML_BASED/__init__.py
anomaly_detection_methods/ML_BASED/logistic_regression_model.pkl
anomaly_detection_methods/ML_BASED/ml_analyzer.py
anomaly_detection_methods/ML_BASED/tfidf_vectorizer.pkl
anomaly_detection_methods/ML_BASED/train_model.py
anomaly_detection_methods/SIGNATURE_BASED/__init__.py
anomaly_detection_methods/SIGNATURE_BASED/signature_analyzer.py
anomaly_detection_methods/SIGNATURE_BASED/signatures.json
anomaly_detection_methods/SIGNATURE_BASED/utils.py
anomaly_detection_methods/tests/ML_tests.py
anomaly_detection_methods/tests/__init__.py
anomaly_detection_methods/tests/signatures_tests.py
dre4my_detection-0.1.3.dist-info/METADATA
dre4my_detection-0.1.3.dist-info/WHEEL
dre4my_detection-0.1.3.dist-info/top_level.txt
dre4my_detection-0.1.3.dist-info/RECORD
